CHANGELOG
LICENSE
MANIFEST.in
README.md
setup.cfg
setup.py
Flask_MarcoPolo.egg-info/PKG-INFO
Flask_MarcoPolo.egg-info/SOURCES.txt
Flask_MarcoPolo.egg-info/dependency_links.txt
Flask_MarcoPolo.egg-info/entry_points.txt
Flask_MarcoPolo.egg-info/not-zip-safe
Flask_MarcoPolo.egg-info/requires.txt
Flask_MarcoPolo.egg-info/top_level.txt
flask_marcopolo/__init__.py
flask_marcopolo/__init__.pyc
flask_marcopolo/cmd.py
flask_marcopolo/pkg.py
flask_marcopolo/pkg.pyc
flask_marcopolo/projects_templates/__init__.py
flask_marcopolo/projects_templates/run_default.py.tpl
flask_marcopolo/projects_templates/default/__init__.py
flask_marcopolo/projects_templates/default/config.py
flask_marcopolo/projects_templates/default/model.py
flask_marcopolo/projects_templates/default/static/css/style.css
flask_marcopolo/projects_templates/default/static/img/blank
flask_marcopolo/projects_templates/default/static/js/app.js
flask_marcopolo/projects_templates/default/static/vendor/bootstrap/css/bootstrap-theme.css
flask_marcopolo/projects_templates/default/static/vendor/bootstrap/css/bootstrap-theme.css.map
flask_marcopolo/projects_templates/default/static/vendor/bootstrap/css/bootstrap-theme.min.css
flask_marcopolo/projects_templates/default/static/vendor/bootstrap/css/bootstrap.css
flask_marcopolo/projects_templates/default/static/vendor/bootstrap/css/bootstrap.css.map
flask_marcopolo/projects_templates/default/static/vendor/bootstrap/css/bootstrap.min.css
flask_marcopolo/projects_templates/default/static/vendor/bootstrap/fonts/glyphicons-halflings-regular.eot
flask_marcopolo/projects_templates/default/static/vendor/bootstrap/fonts/glyphicons-halflings-regular.svg
flask_marcopolo/projects_templates/default/static/vendor/bootstrap/fonts/glyphicons-halflings-regular.ttf
flask_marcopolo/projects_templates/default/static/vendor/bootstrap/fonts/glyphicons-halflings-regular.woff
flask_marcopolo/projects_templates/default/static/vendor/bootstrap/js/bootstrap.js
flask_marcopolo/projects_templates/default/static/vendor/bootstrap/js/bootstrap.min.js
flask_marcopolo/projects_templates/default/static/vendor/bootswatch/README
flask_marcopolo/projects_templates/default/static/vendor/bootswatch/amelia.css
