Metadata-Version: 1.1
Name: Flask-MarcoPolo
Version: 0.6.1
Summary: 
